kimina_client/__init__.py
kimina_client/async_client.py
kimina_client/base.py
kimina_client/client_old.py
kimina_client/import json.py
kimina_client/infotree.py
kimina_client/models.py
kimina_client/proof_utils.py
kimina_client/py.typed
kimina_client/sync_client.py
kimina_client/utils.py
kimina_client-0.2.1.dist-info/METADATA
kimina_client-0.2.1.dist-info/WHEEL
kimina_client-0.2.1.dist-info/licenses/LICENSE
kimina_client-0.2.1.dist-info/RECORD
